CMakeLists.txt
MANIFEST.in
README.md
setup.py
ROL/ROL.cpp
ROL/_ROL.cpython-36m-x86_64-linux-gnu.so
ROL/__init__.py
ROL/algorithm.cpp
ROL/algorithmstate.cpp
ROL/augmentedlagrangian.cpp
ROL/bounds.cpp
ROL/constraint.cpp
ROL/dolfin_vector.py
ROL/firedrake_vector.py
ROL/moreauyosidapenalty.cpp
ROL/numpy_vector.py
ROL/objective.cpp
ROL/optimizationproblem.cpp
ROL/optimizationsolver.cpp
ROL/parameterlist.cpp
ROL/py_shared_ptr.hpp
ROL/stdvector.cpp
ROL/vector.cpp
ROL.egg-info/PKG-INFO
ROL.egg-info/SOURCES.txt
ROL.egg-info/dependency_links.txt
ROL.egg-info/not-zip-safe
ROL.egg-info/top_level.txt
pybind11/.appveyor.yml
pybind11/.git
pybind11/.gitignore
pybind11/.gitmodules
pybind11/.readthedocs.yml
pybind11/.travis.yml
pybind11/CMakeLists.txt
pybind11/CONTRIBUTING.md
pybind11/ISSUE_TEMPLATE.md
pybind11/LICENSE
pybind11/MANIFEST.in
pybind11/README.md
pybind11/setup.cfg
pybind11/setup.py
pybind11/docs/Doxyfile
pybind11/docs/Makefile
pybind11/docs/basics.rst
pybind11/docs/benchmark.py
pybind11/docs/benchmark.rst
pybind11/docs/changelog.rst
pybind11/docs/classes.rst
pybind11/docs/compiling.rst
pybind11/docs/conf.py
pybind11/docs/faq.rst
pybind11/docs/index.rst
pybind11/docs/intro.rst
pybind11/docs/limitations.rst
pybind11/docs/pybind11-logo.png
pybind11/docs/pybind11_vs_boost_python1.png
pybind11/docs/pybind11_vs_boost_python1.svg
pybind11/docs/pybind11_vs_boost_python2.png
pybind11/docs/pybind11_vs_boost_python2.svg
pybind11/docs/reference.rst
pybind11/docs/release.rst
pybind11/docs/requirements.txt
pybind11/docs/upgrade.rst
pybind11/docs/_static/theme_overrides.css
pybind11/docs/advanced/classes.rst
pybind11/docs/advanced/embedding.rst
pybind11/docs/advanced/exceptions.rst
pybind11/docs/advanced/functions.rst
pybind11/docs/advanced/misc.rst
pybind11/docs/advanced/smart_ptrs.rst
pybind11/docs/advanced/cast/chrono.rst
pybind11/docs/advanced/cast/custom.rst
pybind11/docs/advanced/cast/eigen.rst
pybind11/docs/advanced/cast/functional.rst
pybind11/docs/advanced/cast/index.rst
pybind11/docs/advanced/cast/overview.rst
pybind11/docs/advanced/cast/stl.rst
pybind11/docs/advanced/cast/strings.rst
