Metadata-Version: 1.0
Name: ROL
Version: 0.0.16
Summary: A python wrapper for the ROL package.
Home-page: UNKNOWN
Author: Chris Richardson, Greg von Winckel, Florian Wechsung
Author-email: wechsung@maths.ox.ac.uk
License: UNKNOWN
Platform: UNKNOWN
